Metadata-Version: 2.1
Name: tflite2onnx
Version: 0.4.1
Summary: Convert TensorFlow Lite models to ONNX
Home-page: https://zhenhuaw.me/tflite2onnx
Author: 王振华(Zhenhua WANG)
Author-email: hi@zhenhuaw.me
License: Apache License 2.0
Project-URL: Bug Reports, https://github.com/zhenhuaw-me/tflite2onnx/issues
Project-URL: Source, https://github.com/zhenhuaw-me/tflite2onnx
Keywords: tflite,onnx,deep-learning
Classifier: Development Status :: 4 - Beta
Classifier: Programming Language :: Python :: 3
Classifier: Programming Language :: Python :: 3.5
Classifier: Programming Language :: Python :: 3.6
Classifier: Programming Language :: Python :: 3.7
Classifier: Programming Language :: Python :: 3.8
Classifier: Environment :: Console
Classifier: Intended Audience :: Developers
Classifier: License :: OSI Approved :: Apache Software License
Classifier: Natural Language :: English
Classifier: Operating System :: OS Independent
Classifier: Topic :: Scientific/Engineering :: Artificial Intelligence
Requires-Python: <4,>=3.5.*
License-File: LICENSE
